MANIFEST.in
README.md
requirements.txt
setup.py
optimus/__init__.py
optimus/config.py
optimus/data_map.py
optimus/exception.py
optimus/optimus.py
optimus/requestor.py
optimus/schemas.py
optimus/utils.py
optimus_sdk.egg-info/PKG-INFO
optimus_sdk.egg-info/SOURCES.txt
optimus_sdk.egg-info/dependency_links.txt
optimus_sdk.egg-info/requires.txt
optimus_sdk.egg-info/top_level.txt
test/test.py