Metadata-Version: 2.1
Name: optimus-sdk
Version: 0.0.23
Summary: Optimus SDK
Home-page: https://aiexcelsior.art/
Author: unianalysis
Author-email: contact@unianalysis.com
License: UNKNOWN
Platform: UNKNOWN
Classifier: Development Status :: 5 - Production/Stable
Classifier: Intended Audience :: Developers
Classifier: License :: OSI Approved :: MIT License
Classifier: Operating System :: OS Independent
Classifier: Programming Language :: Python
Classifier: Topic :: Software Development :: Libraries :: Python Modules
